README.md
setup.py
tsuru_sphinx/__init__.py
tsuru_sphinx.egg-info/PKG-INFO
tsuru_sphinx.egg-info/SOURCES.txt
tsuru_sphinx.egg-info/dependency_links.txt
tsuru_sphinx.egg-info/entry_points.txt
tsuru_sphinx.egg-info/requires.txt
tsuru_sphinx.egg-info/top_level.txt
tsuru_sphinx/handlers/__init__.py