Metadata-Version: 1.1
Name: tsuru-sphinx
Version: 0.1.5
Summary: Sphinx extensions used in tsuru documentation
Home-page: https://github.com/tsuru/tsuru-sphinx
Author: Tsuru
Author-email: tsuru@corp.globo.com
License: UNKNOWN
Platform: UNKNOWN
Classifier: Programming Language :: Python :: 2.7
